slidegrubber/__init__.py
slidegrubber/grub.py
slidegrubber-2.7.dist-info/LICENSE
slidegrubber-2.7.dist-info/METADATA
slidegrubber-2.7.dist-info/WHEEL
slidegrubber-2.7.dist-info/top_level.txt
slidegrubber-2.7.dist-info/RECORD
