Metadata-Version: 2.1
Name: slidegrubber
Version: 2.7
Summary: Back up your SlideShare presentations to PDF.
Home-page: https://github.com/cballenar/slidegrubber
Author: Carlos Ballena
Author-email: cballenar@gmail.com
License: MIT
Keywords: slideshare download pdf python
Platform: UNKNOWN
Classifier: Development Status :: 5 - Production/Stable
Classifier: Environment :: Console
Classifier: License :: Free for non-commercial use
Classifier: Natural Language :: English
Classifier: Programming Language :: Python :: 2.7
Classifier: Topic :: Utilities
Requires-Dist: Wand
Requires-Dist: requests
Requires-Dist: beautifulsoup4
